sslspy/__init__.py
sslspy/__main__.py
sslspy/checker.py
sslspy/cli.py
sslspy/constants.py
sslspy/ui.py
sslspy/utils.py
sslspy-1.1.0.dist-info/licenses/LICENSE
sslspy-1.1.0.dist-info/METADATA
sslspy-1.1.0.dist-info/WHEEL
sslspy-1.1.0.dist-info/entry_points.txt
sslspy-1.1.0.dist-info/top_level.txt
sslspy-1.1.0.dist-info/RECORD
