Metadata-Version: 2.4
Name: sslspy
Version: 1.1.0
Summary: A comprehensive SSL/TLS security scanner for analyzing certificates, protocols, and security vulnerabilities.
Author-email: Ehsan Ul Haq Khawja <ehsanulhaqkhawja01@gmail.com>
License: MIT
Project-URL: Homepage, https://github.com/ehsanulhaq001/sslspy
Project-URL: BugTracker, https://github.com/ehsanulhaq001/sslspy/issues
Keywords: ssl,tls,certificate,security,scanner,cipher,protocol
Classifier: Programming Language :: Python :: 3
Classifier: Topic :: Security :: Cryptography
Classifier: Intended Audience :: System Administrators
Classifier: License :: OSI Approved :: MIT License
Requires-Python: >=3.7
License-File: LICENSE
Requires-Dist: colorama>=0.4.0
Dynamic: license-file
